Exercises/ex07/ex07.vhdl
-- Ramtin Kosari - 40021441054102 - Seven Segment Display
library IEEE;library IEEE;
use IEEE.STD_LOGIC_1164.all;

entity seven_segment_decoder is
    port(
        data : in STD_LOGIC_VECTOR(4 downto 0); 
        segments : out STD_LOGIC_VECTOR(13 downto 0)
    ); 
end;

architecture synth of seven_segment_decoder is
begin
    process(all) begin
        case data is
            when "00000" => segments <= "00000001111110"; -- 0
            when "00001" => segments <= "00000000110000"; -- 1
            when "00010" => segments <= "00000001101101"; -- 2
            when "00011" => segments <= "00000001111101"; -- 3
            when "00100" => segments <= "00000001110001"; -- 4
            when "00101" => segments <= "00000001111011"; -- 5
            when "00110" => segments <= "00000001111011"; -- 6
            when "00111" => segments <= "00000001100000"; -- 7
            when "01000" => segments <= "00000001111111"; -- 8
            when "01001" => segments <= "00000001110001"; -- 9
            when "01010" => segments <= "01100001111110"; -- 10
            when "01011" => segments <= "01100000110000"; -- 11
            when "01100" => segments <= "01100001101101"; -- 12
            when "01101" => segments <= "01100001111001"; -- 13
            when "01110" => segments <= "01100000110011"; -- 14
            when "01111" => segments <= "01100001011011"; -- 15
            when "10000" => segments <= "01100001011111"; -- 16
            when "10001" => segments <= "01100001110000"; -- 17
            when "10010" => segments <= "01100001111111"; -- 18
            when "10011" => segments <= "01100001110011"; -- 19
            when "10100" => segments <= "11011011111110"; -- 20
            when others => segments <= "00000000000000"; -- Off
        end case;
    end process;
end;

Exercises/ex07/tb.vhdl
-- Ramtin Kosari - 40021441054102 - Seven Segment Display
library IEEE;
use IEEE.STD_LOGIC_1164.ALL;
use IEEE.NUMERIC_STD.ALL;

entity tb is
end tb;

architecture behavior of tb is
    component seven_segment_decoder is
        port(
            data     : in  STD_LOGIC_VECTOR(4 downto 0);
            segments : out STD_LOGIC_VECTOR(13 downto 0)
        );
    end component;
    signal data     : STD_LOGIC_VECTOR(4 downto 0) := (others => '0');
    signal segments : STD_LOGIC_VECTOR(13 downto 0);
begin
    uut: seven_segment_decoder
        port map (
            data     => data,
            segments => segments
        );
    stim_proc: process
    begin
        -- Loop Through All Values from 0 to 20
        for i in 0 to 20 loop
            data <= std_logic_vector(to_unsigned(i, data'length));
            wait for 10 ns;
        end loop;
        -- Test Others
        data <= "10101";
        wait for 10 ns;
        wait;
    end process;
end behavior;

Exercises/ex07/wave.vcd
$date
  Mon May 26 02:10:16 2025
$end
$version
  GHDL v0
$end
$timescale
  1 fs
$end
$scope module standard $end
$upscope $end
$scope module textio $end
$upscope $end
$scope module std_logic_1164 $end
$upscope $end
$scope module numeric_std $end
$upscope $end
$scope module tb $end
$var reg 5 ! data[4:0] $end
$var reg 14 " segments[13:0] $end
$scope module uut $end
$var reg 5 # data[4:0] $end
$var reg 14 $ segments[13:0] $end
$upscope $end
$upscope $end
$enddefinitions $end
#0
b00000 !
b00000001111110 "
b00000 #
b00000001111110 $
#10000000
b00001 !
b00000000110000 "
b00001 #
b00000000110000 $
#20000000
b00010 !
b00000001101101 "
b00010 #
b00000001101101 $
#30000000
b00011 !
b00000001111101 "
b00011 #
b00000001111101 $
#40000000
b00100 !
b00000001110001 "
b00100 #
b00000001110001 $
#50000000
b00101 !
b00000001111011 "
b00101 #
b00000001111011 $
#60000000
b00110 !
b00110 #
#70000000
b00111 !
b00000001100000 "
b00111 #
b00000001100000 $
#80000000
b01000 !
b00000001111111 "
b01000 #
b00000001111111 $
#90000000
b01001 !
b00000001110001 "
b01001 #
b00000001110001 $
#100000000
b01010 !
b01100001111110 "
b01010 #
b01100001111110 $
#110000000
b01011 !
b01100000110000 "
b01011 #
b01100000110000 $
#120000000
b01100 !
b01100001101101 "
b01100 #
b01100001101101 $
#130000000
b01101 !
b01100001111001 "
b01101 #
b01100001111001 $
#140000000
b01110 !
b01100000110011 "
b01110 #
b01100000110011 $
#150000000
b01111 !
b01100001011011 "
b01111 #
b01100001011011 $
#160000000
b10000 !
b01100001011111 "
b10000 #
b01100001011111 $
#170000000
b10001 !
b01100001110000 "
b10001 #
b01100001110000 $
#180000000
b10010 !
b01100001111111 "
b10010 #
b01100001111111 $
#190000000
b10011 !
b01100001110011 "
b10011 #
b01100001110011 $
#200000000
b10100 !
b11011011111110 "
b10100 #
b11011011111110 $
#210000000
b10101 !
b00000000000000 "
b10101 #
b00000000000000 $
