Exercises/ex06/ex06.vhdl
-- Ramtin Kosari - 40021441054102 - shiftreg4_async
library IEEE;
use IEEE.STD_LOGIC_1164.ALL;

entity shiftreg4_async is
    port(
        clk     : in  STD_LOGIC;
        reset   : in  STD_LOGIC;
        load    : in  STD_LOGIC;
        sin     : in  STD_LOGIC;
        d       : in  STD_LOGIC_VECTOR(3 downto 0);
        q       : out STD_LOGIC_VECTOR(3 downto 0);
        sout    : out STD_LOGIC
    );
end entity;

architecture synth of shiftreg4_async is
    signal q_reg : STD_LOGIC_VECTOR(3 downto 0);
begin
    process(clk, reset)
    begin
        if reset = '1' then
            q_reg <= (others => '0');
        elsif rising_edge(clk) then
            if load = '1' then
                q_reg <= d;
            else
                q_reg <= q_reg(2 downto 0) & sin;
            end if;
        end if;
    end process;

    q <= q_reg;
    sout <= q_reg(3);
end architecture;

Exercises/ex06/tb.vhdl
-- Testbench for shiftreg4_async
library IEEE;
use IEEE.STD_LOGIC_1164.ALL;

entity tb is
end entity;

architecture sim of tb is

    -- Component Declaration
    component shiftreg4_async
        port(
            clk     : in  STD_LOGIC;
            reset   : in  STD_LOGIC;
            load    : in  STD_LOGIC;
            sin     : in  STD_LOGIC;
            d       : in  STD_LOGIC_VECTOR(3 downto 0);
            q       : out STD_LOGIC_VECTOR(3 downto 0);
            sout    : out STD_LOGIC
        );
    end component;

    -- Signals for testing
    signal clk     : STD_LOGIC := '0';
    signal reset   : STD_LOGIC := '0';
    signal load    : STD_LOGIC := '0';
    signal sin     : STD_LOGIC := '0';
    signal d       : STD_LOGIC_VECTOR(3 downto 0) := (others => '0');
    signal q       : STD_LOGIC_VECTOR(3 downto 0);
    signal sout    : STD_LOGIC;

    -- Clock period
    constant clk_period : time := 10 ns;

begin

    -- Instantiate the DUT
    uut: shiftreg4_async
        port map (
            clk   => clk,
            reset => reset,
            load  => load,
            sin   => sin,
            d     => d,
            q     => q,
            sout  => sout
        );

    -- Clock generation
    clk_process : process
    begin
        while now < 200 ns loop
            clk <= '0';
            wait for clk_period / 2;
            clk <= '1';
            wait for clk_period / 2;
        end loop;
        wait;
    end process;

    -- Stimulus process
    stim_proc: process
    begin
        -- Apply asynchronous reset
        reset <= '1';
        wait for 7 ns;
        reset <= '0';
        wait for clk_period;

        -- Parallel load
        d <= "1010";
        load <= '1';
        wait for clk_period;
        load <= '0';

        -- Shift in serial bits
        sin <= '1';
        wait for clk_period;
        sin <= '0';
        wait for clk_period;
        sin <= '1';
        wait for clk_period;
        sin <= '1';
        wait for clk_period;

        -- Reset again in the middle
        reset <= '1';
        wait for 5 ns;
        reset <= '0';

        wait;
    end process;

end architecture;

Exercises/ex06/wave.vcd
$date
  Mon May 19 02:47:31 2025
$end
$version
  GHDL v0
$end
$timescale
  1 fs
$end
$scope module standard $end
$upscope $end
$scope module std_logic_1164 $end
$upscope $end
$scope module tb $end
$var reg 1 ! clk $end
$var reg 1 " reset $end
$var reg 1 # load $end
$var reg 1 $ sin $end
$var reg 4 % d[3:0] $end
$var reg 4 & q[3:0] $end
$var reg 1 ' sout $end
$scope module uut $end
$var reg 1 ( clk $end
$var reg 1 ) reset $end
$var reg 1 * load $end
$var reg 1 + sin $end
$var reg 4 , d[3:0] $end
$var reg 4 - q[3:0] $end
$var reg 1 . sout $end
$var reg 4 / q_reg[3:0] $end
$upscope $end
$upscope $end
$enddefinitions $end
#0
0!
1"
0#
0$
b0000 %
b0000 &
0'
0(
1)
0*
0+
b0000 ,
b0000 -
0.
b0000 /
#5000000
1!
1(
#7000000
0"
0)
#10000000
0!
0(
#15000000
1!
1(
#17000000
1#
b1010 %
1*
b1010 ,
#20000000
0!
0(
#25000000
1!
b1010 &
1'
1(
b1010 -
1.
b1010 /
#27000000
0#
1$
0*
1+
#30000000
0!
0(
#35000000
1!
b0101 &
0'
1(
b0101 -
0.
b0101 /
#37000000
0$
0+
#40000000
0!
0(
#45000000
1!
b1010 &
1'
1(
b1010 -
1.
b1010 /
#47000000
1$
1+
#50000000
0!
0(
#55000000
1!
b0101 &
0'
1(
b0101 -
0.
b0101 /
#57000000
#60000000
0!
0(
#65000000
1!
b1011 &
1'
1(
b1011 -
1.
b1011 /
#67000000
1"
b0000 &
0'
1)
b0000 -
0.
b0000 /
#70000000
0!
0(
#72000000
0"
0)
#75000000
1!
b0001 &
1(
b0001 -
b0001 /
#80000000
0!
0(
#85000000
1!
b0011 &
1(
b0011 -
b0011 /
#90000000
0!
0(
#95000000
1!
b0111 &
1(
b0111 -
b0111 /
#100000000
0!
0(
#105000000
1!
b1111 &
1'
1(
b1111 -
1.
b1111 /
