Exercises/ex03/ex03.vhdl
-- Ramtin Kosari - 40021441054102 - ex02
library IEEE;
use IEEE.STD_LOGIC_1164.all;

-- Define Entity
entity ex03 is
    port (
        -- Inputs
        a, b, c     : in STD_LOGIC;
        -- Output
        y           : out STD_LOGIC
    );
end ex03;

-- Define Architecture
architecture Behavioral of ex03 is
    signal ab, bb, cb, n1, n2, n3: STD_LOGIC;
begin
    ab <= not a after 5 ns;
    bb <= not b after 5 ns;
    cb <= not c after 5 ns;
    n1 <= ab and bb and cb after 10 ns;
    n2 <= a and bb and cb after 10 ns;
    n3 <= a and bb and c after 10 ns;
    y  <= n1 or n2 or n3 after 20 ns;
end Behavioral;

Exercises/ex03/tb.vhdl
-- Ramtin Kosari - 40021441054102 - ex03
library IEEE;
use IEEE.STD_LOGIC_1164.ALL;
use IEEE.NUMERIC_STD.ALL;

entity tb is
end tb;

architecture Behavioral of tb is
    -- Define Signals
    signal a, b, c : std_logic;
    signal y       : std_logic;
    
    -- Instantiate the Circuit
    component ex03
        Port (
            a : in  std_logic;
            b : in  std_logic;
            c : in  std_logic;
            y : out std_logic
        );
    end component;
    -- Method to Convert Vector to String
    function to_string(s : std_logic) return string is
    begin
        return std_ulogic'image(s);
    end function;
begin
    -- Connect signals to component
    uut: ex03
        port map (
            a => a,
            b => b,
            c => c,
            y => y
        );

    -- Test Process
    process
    begin
        -- Test Case 1
        a <= '0';
        b <= '0';
        c <= '0';
        wait for 10 ns;
        
        -- Test Case 2
        a <= '0';
        b <= '0';
        c <= '1';
        wait for 10 ns;
        
        -- Test Case 3
        a <= '0';
        b <= '1';
        c <= '0';
        wait for 10 ns;
        
        -- Test Case 4
        a <= '0';
        b <= '1';
        c <= '1';
        wait for 10 ns;
        -- Test Case 5
        a <= '1';
        b <= '0';
        c <= '0';
        wait for 10 ns;
        -- Test Case 6
        a <= '1';
        b <= '0';
        c <= '1';
        wait for 10 ns;
        -- Test Case 7
        a <= '1';
        b <= '1';
        c <= '0';
        wait for 10 ns;
        -- Test Case 8
        a <= '1';
        b <= '1';
        c <= '1';
        wait for 10 ns;
        -- Report Results
        report "Test Case 1: a = " & to_string(a) & 
               " | b = " & to_string(b) & 
               " | c = " & to_string(c) & 
               " | y = " & to_string(y);
        report "Test Case 2: a = " & to_string(a) &
               " | b = " & to_string(b) & 
               " | c = " & to_string(c) & 
               " | y = " & to_string(y);
        report "Test Case 3: a = " & to_string(a) &
               " | b = " & to_string(b) & 
               " | c = " & to_string(c) & 
               " | y = " & to_string(y);
        report "Test Case 4: a = " & to_string(a) &
               " | b = " & to_string(b) & 
               " | c = " & to_string(c) & 
               " | y = " & to_string(y);
        report "Test Case 5: a = " & to_string(a) &
               " | b = " & to_string(b) & 
               " | c = " & to_string(c) & 
               " | y = " & to_string(y);
        report "Test Case 6: a = " & to_string(a) &
               " | b = " & to_string(b) & 
               " | c = " & to_string(c) & 
               " | y = " & to_string(y);
        report "Test Case 7: a = " & to_string(a) &
               " | b = " & to_string(b) & 
               " | c = " & to_string(c) & 
               " | y = " & to_string(y);
        report "Test Case 8: a = " & to_string(a) &
               " | b = " & to_string(b) & 
               " | c = " & to_string(c) & 
               " | y = " & to_string(y);
        wait;
    end process;
end Behavioral;

Exercises/ex03/simulation.vcd
$date
  Sun May 18 23:26:24 2025
$end
$version
  GHDL v0
$end
$timescale
  1 fs
$end
$scope module standard $end
$upscope $end
$scope module std_logic_1164 $end
$upscope $end
$scope module numeric_std $end
$upscope $end
$scope module tb $end
$var reg 1 ! a $end
$var reg 1 " b $end
$var reg 1 # c $end
$var reg 1 $ y $end
$scope module uut $end
$var reg 1 % a $end
$var reg 1 & b $end
$var reg 1 ' c $end
$var reg 1 ( y $end
$var reg 1 ) ab $end
$var reg 1 * bb $end
$var reg 1 + cb $end
$var reg 1 , n1 $end
$var reg 1 - n2 $end
$var reg 1 . n3 $end
$upscope $end
$upscope $end
$enddefinitions $end
#0
0!
0"
0#
U$
0%
0&
0'
U(
U)
U*
U+
U,
U-
U.
#5000000
1)
1*
1+
#10000000
1#
1'
0-
0.
#15000000
0+
1,
#20000000
1"
0#
1&
0'
#25000000
0*
1+
0,
#30000000
1#
1'
#35000000
0+
#40000000
1!
0"
0#
1%
0&
0'
#45000000
0$
0(
0)
1*
1+
#50000000
1#
1'
#55000000
0+
1-
#60000000
1"
0#
1&
0'
1.
#65000000
0*
1+
0-
#70000000
1#
1'
0.
#75000000
0+
#80000000
#85000000
#90000000
0(
